LICENSE
MANIFEST.in
README-CN.md
README.md
pytest.ini
requirements.txt
setup.py
handyML/__init__.py
handyML.egg-info/PKG-INFO
handyML.egg-info/SOURCES.txt
handyML.egg-info/dependency_links.txt
handyML.egg-info/requires.txt
handyML.egg-info/top_level.txt
handyML/Exploratory_data_analysis/Exploratory_data_analysis.py
handyML/Exploratory_data_analysis/__init__.py
handyML/ensemble/__init__.py
handyML/feature_engineering/__init__.py
handyML/feature_engineering/uniform_to_barrel.py
handyML/models/__init__.py
handyML/models/model.py
handyML/params_opt/__init__.py
handyML/params_opt/bayes_opt.py
handyML/preprocessing/Encoding.py
handyML/preprocessing/__init__.py
tests/__init__.py
tests/test_Exploratory_data_analysis.py
tests/test_load_data.py
tests/test_preprocessing.py