Metadata-Version: 2.1
Name: handyML
Version: 0.0.1b1
Summary: A library for data science
Home-page: https://github.com/leo6033/handyML
Author: ITryagain
Author-email: long452a@163.com
License: UNKNOWN
Platform: UNKNOWN
Classifier: Programming Language :: Python :: 3
Classifier: License :: OSI Approved :: MIT License
Classifier: Operating System :: OS Independent
Requires-Python: >=3.6.0
